SPI.v

module spi_module (
  // Провода, которые идут вовне из модуля
  input sck,      // Serial Clock
  inout cs,       // Chip Select
  inout mosi,     // Master Out Slave In 
  inout miso,     // Master In Slave Out
  // Параметры, задаваемые устройством, которое использует модуль
  input p_master,        // Является ли модуль передатчиком (Master-ом)
  input [7:0]p_data_in,  // Входные данные для передачи
  output [7:0]p_data_out // Выходные данные для чтения
  );
  
  reg [7:0]data;  // Регистр с передаваемым байтом
  reg [3:0]ptr;   // Указатель на передаваемый бит
  reg out;        // Выходной регистр
  
  assign mosi = p_master ? out : 1'bz;
  assign p_data_out = data;
  assign cs = p_master ? !(ptr == 4'd0) : 1'bz; // Master в первый и второй такт устанавливает сброс по CS, затем начинает передачу
  
  always @(negedge sck)
  begin
    if (p_master) // Если Master то выдаём новый бит данных на выход
    begin
      out = data >> ptr;
      ptr = ptr + 1;
      if (ptr == 4'd9) ptr = 4'd0;
    end
  end

  always @(posedge sck)
  begin

    if (!p_master & cs) // Если CS=1 то принимаем бит
    begin
      if (ptr < 8)
      begin
        data[ptr] = mosi;
        ptr = ptr + 1;
      end
      // if (ptr = 8) {управляющее устройство забирает данные}
    end

    if (!cs & p_master) // Если CS=0 то по такту SCK принимаем новый байт данных из управляющего устройства
    begin
      data[7:0] <= p_data_in;
    end
  end
  
  always @(negedge cs & !p_master) // Slave по сбросу обнуляет данные
  begin
    data[7:0] <= 8'b00000000;
    ptr[3:0] <= 4'b0000;
    out <= 1'bz;
  end

endmodule

Testbench.v
`timescale 1ns/1ps

module spi_testbench();

reg clock;
reg reset;

wire miso;
wire mosi;
wire cs;

// Инициализируем переменные
initial begin
  $dumpfile("out.vcd");
  $dumpvars(0, spi_testbench);
  clock = 0;       // Начальное значнеие для clock
  reset = 0;       // Начальное значнеие для reset
  // Тактирование
  #2 reset = 0;    // Установка сброса
  #3 reset = 1;    // Снятие сброса
  #496 reset = 0;  // Установка сброса
  #500 $finish;    // Конец симуляции
end

// Тактовый генератор
always begin
  #2 clock = ~clock;
end

// Присоединяем модули
spi_module spi_m (.sck(clock), .cs(cs), .mosi(mosi), .miso(miso), .p_master(1'b1), .p_data_in(8'b11101001));
spi_module spi_s (.sck(clock), .cs(cs), .mosi(mosi), .miso(miso), .p_master(1'b0));

endmodule

out.vcd
$date
	Thu Feb 02 02:34:35 2017
$end
$version
	Icarus Verilog
$end
$timescale
	1ps
$end
$scope module spi_testbench $end
$var wire 1 ! cs $end
$var wire 1 " miso $end
$var wire 1 # mosi $end
$var reg 1 $ clock $end
$var reg 1 % reset $end
$scope module spi_m $end
$var wire 1 ! cs $end
$var wire 1 " miso $end
$var wire 1 # mosi $end
$var wire 8 & p_data_in [7:0] $end
$var wire 8 ' p_data_out [7:0] $end
$var wire 1 ( p_master $end
$var wire 1 $ sck $end
$var reg 8 ) data [7:0] $end
$var reg 1 * out $end
$var reg 4 + ptr [3:0] $end
$upscope $end
$scope module spi_s $end
$var wire 1 ! cs $end
$var wire 1 " miso $end
$var wire 1 # mosi $end
$var wire 8 , p_data_in [7:0] $end
$var wire 8 - p_data_out [7:0] $end
$var wire 1 . p_master $end
$var wire 1 $ sck $end
$var reg 8 / data [7:0] $end
$var reg 1 0 out $end
$var reg 4 1 ptr [3:0] $end
$upscope $end
$upscope $end
$enddefinitions $end
#0
$dumpvars
b0 1
z0
b0 /
0.
b0 -
bz ,
b0 +
z*
b0 )
1(
b0 '
b11101001 &
0%
0$
z#
z"
0!
$end
#2000
b11101001 '
b11101001 )
1$
#4000
1!
b1 +
1#
1*
0$
#5000
1%
#6000
b1 1
b1 -
b1 /
1$
#8000
b10 +
0#
0*
0$
#10000
b10 1
1$
#12000
b11 +
0$
#14000
b11 1
1$
#16000
b100 +
1#
1*
0$
#18000
b100 1
b1001 -
b1001 /
1$
#20000
b101 +
0#
0*
0$
#22000
b101 1
1$
#24000
b110 +
1#
1*
0$
#26000
b110 1
b101001 -
b101001 /
1$
#28000
b111 +
0$
#30000
b111 1
b1101001 -
b1101001 /
1$
#32000
b1000 +
0$
#34000
b1000 1
b11101001 -
b11101001 /
1$
#36000
b0 1
b0 -
b0 /
0!
b0 +
0#
0*
0$
#38000
1$
#40000
1!
b1 +
1#
1*
0$
#42000
b1 1
b1 -
b1 /
1$
#44000
b10 +
0#
0*
0$
#46000
b10 1
1$
#48000
b11 +
0$
#50000
b11 1
1$
#52000
b100 +
1#
1*
0$
#54000
b100 1
b1001 -
b1001 /
1$
#56000
b101 +
0#
0*
0$
#58000
b101 1
1$
#60000
b110 +
1#
1*
0$
#62000
b110 1
b101001 -
b101001 /
1$
#64000
b111 +
0$
#66000
b111 1
b1101001 -
b1101001 /
1$
#68000
b1000 +
0$
#70000
b1000 1
b11101001 -
b11101001 /
1$
#72000
b0 1
b0 -
b0 /
0!
b0 +
0#
0*
0$
#74000
1$
#76000
1!
b1 +
1#
1*
0$
#78000
b1 1
b1 -
b1 /
1$
#80000
b10 +
0#
0*
0$
#82000
b10 1
1$
#84000
b11 +
0$
#86000
b11 1
1$
#88000
b100 +
1#
1*
0$
#90000
b100 1
b1001 -
b1001 /
1$
#92000
b101 +
0#
0*
0$
#94000
b101 1
1$
#96000
b110 +
1#
1*
0$
#98000
b110 1
b101001 -
b101001 /
1$
#100000
b111 +
0$
#102000
b111 1
b1101001 -
b1101001 /
1$
#104000
b1000 +
0$
#106000
b1000 1
b11101001 -
b11101001 /
1$
#108000
b0 1
b0 -
b0 /
0!
b0 +
0#
0*
0$
#110000
1$
#112000
1!
b1 +
1#
1*
0$
#114000
b1 1
b1 -
b1 /
1$
#116000
b10 +
0#
0*
0$
#118000
b10 1
1$
#120000
b11 +
0$
#122000
b11 1
1$
#124000
b100 +
1#
1*
0$
#126000
b100 1
b1001 -
b1001 /
1$
#128000
b101 +
0#
0*
0$
#130000
b101 1
1$
#132000
b110 +
1#
1*
0$
#134000
b110 1
b101001 -
b101001 /
1$
#136000
b111 +
0$
#138000
b111 1
b1101001 -
b1101001 /
1$
#140000
b1000 +
0$
#142000
b1000 1
b11101001 -
b11101001 /
1$
#144000
b0 1
b0 -
b0 /
0!
b0 +
0#
0*
0$
#146000
1$
#148000
1!
b1 +
1#
1*
0$
#150000
b1 1
b1 -
b1 /
1$
#152000
b10 +
0#
0*
0$
#154000
b10 1
1$
#156000
b11 +
0$
#158000
b11 1
1$
#160000
b100 +
1#
1*
0$
#162000
b100 1
b1001 -
b1001 /
1$
#164000
b101 +
0#
0*
0$
#166000
b101 1
1$
#168000
b110 +
1#
1*
0$
#170000
b110 1
b101001 -
b101001 /
1$
#172000
b111 +
0$
#174000
b111 1
b1101001 -
b1101001 /
1$
#176000
b1000 +
0$
#178000
b1000 1
b11101001 -
b11101001 /
1$
#180000
b0 1
b0 -
b0 /
0!
b0 +
0#
0*
0$
#182000
1$
#184000
1!
b1 +
1#
1*
0$
#186000
b1 1
b1 -
b1 /
1$
#188000
b10 +
0#
0*
0$
#190000
b10 1
1$
#192000
b11 +
0$
#194000
b11 1
1$
#196000
b100 +
1#
1*
0$
#198000
b100 1
b1001 -
b1001 /
1$
#200000
b101 +
0#
0*
0$
#202000
b101 1
1$
#204000
b110 +
1#
1*
0$
#206000
b110 1
b101001 -
b101001 /
1$
#208000
b111 +
0$
#210000
b111 1
b1101001 -
b1101001 /
1$
#212000
b1000 +
0$
#214000
b1000 1
b11101001 -
b11101001 /
1$
#216000
b0 1
b0 -
b0 /
0!
b0 +
0#
0*
0$
#218000
1$
#220000
1!
b1 +
1#
1*
0$
#222000
b1 1
b1 -
b1 /
1$
#224000
b10 +
0#
0*
0$
#226000
b10 1
1$
#228000
b11 +
0$
#230000
b11 1
1$
#232000
b100 +
1#
1*
0$
#234000
b100 1
b1001 -
b1001 /
1$
#236000
b101 +
0#
0*
0$
#238000
b101 1
1$
#240000
b110 +
1#
1*
0$
#242000
b110 1
b101001 -
b101001 /
1$
#244000
b111 +
0$
#246000
b111 1
b1101001 -
b1101001 /
1$
#248000
b1000 +
0$
#250000
b1000 1
b11101001 -
b11101001 /
1$
#252000
b0 1
b0 -
b0 /
0!
b0 +
0#
0*
0$
#254000
1$
#256000
1!
b1 +
1#
1*
0$
#258000
b1 1
b1 -
b1 /
1$
#260000
b10 +
0#
0*
0$
#262000
b10 1
1$
#264000
b11 +
0$
#266000
b11 1
1$
#268000
b100 +
1#
1*
0$
#270000
b100 1
b1001 -
b1001 /
1$
#272000
b101 +
0#
0*
0$
#274000
b101 1
1$
#276000
b110 +
1#
1*
0$
#278000
b110 1
b101001 -
b101001 /
1$
#280000
b111 +
0$
#282000
b111 1
b1101001 -
b1101001 /
1$
#284000
b1000 +
0$
#286000
b1000 1
b11101001 -
b11101001 /
1$
#288000
b0 1
b0 -
b0 /
0!
b0 +
0#
0*
0$
#290000
1$
#292000
1!
b1 +
1#
1*
0$
#294000
b1 1
b1 -
b1 /
1$
#296000
b10 +
0#
0*
0$
#298000
b10 1
1$
#300000
b11 +
0$
#302000
b11 1
1$
#304000
b100 +
1#
1*
0$
#306000
b100 1
b1001 -
b1001 /
1$
#308000
b101 +
0#
0*
0$
#310000
b101 1
1$
#312000
b110 +
1#
1*
0$
#314000
b110 1
b101001 -
b101001 /
1$
#316000
b111 +
0$
#318000
b111 1
b1101001 -
b1101001 /
1$
#320000
b1000 +
0$
#322000
b1000 1
b11101001 -
b11101001 /
1$
#324000
b0 1
b0 -
b0 /
0!
b0 +
0#
0*
0$
#326000
1$
#328000
1!
b1 +
1#
1*
0$
#330000
b1 1
b1 -
b1 /
1$
#332000
b10 +
0#
0*
0$
#334000
b10 1
1$
#336000
b11 +
0$
#338000
b11 1
1$
#340000
b100 +
1#
1*
0$
#342000
b100 1
b1001 -
b1001 /
1$
#344000
b101 +
0#
0*
0$
#346000
b101 1
1$
#348000
b110 +
1#
1*
0$
#350000
b110 1
b101001 -
b101001 /
1$
#352000
b111 +
0$
#354000
b111 1
b1101001 -
b1101001 /
1$
#356000
b1000 +
0$
#358000
b1000 1
b11101001 -
b11101001 /
1$
#360000
b0 1
b0 -
b0 /
0!
b0 +
0#
0*
0$
#362000
1$
#364000
1!
b1 +
1#
1*
0$
#366000
b1 1
b1 -
b1 /
1$
#368000
b10 +
0#
0*
0$
#370000
b10 1
1$
#372000
b11 +
0$
#374000
b11 1
1$
#376000
b100 +
1#
1*
0$
#378000
b100 1
b1001 -
b1001 /
1$
#380000
b101 +
0#
0*
0$
#382000
b101 1
1$
#384000
b110 +
1#
1*
0$
#386000
b110 1
b101001 -
b101001 /
1$
#388000
b111 +
0$
#390000
b111 1
b1101001 -
b1101001 /
1$
#392000
b1000 +
0$
#394000
b1000 1
b11101001 -
b11101001 /
1$
#396000
b0 1
b0 -
b0 /
0!
b0 +
0#
0*
0$
#398000
1$
#400000
1!
b1 +
1#
1*
0$
#402000
b1 1
b1 -
b1 /
1$
#404000
b10 +
0#
0*
0$
#406000
b10 1
1$
#408000
b11 +
0$
#410000
b11 1
1$
#412000
b100 +
1#
1*
0$
#414000
b100 1
b1001 -
b1001 /
1$
#416000
b101 +
0#
0*
0$
#418000
b101 1
1$
#420000
b110 +
1#
1*
0$
#422000
b110 1
b101001 -
b101001 /
1$
#424000
b111 +
0$
#426000
b111 1
b1101001 -
b1101001 /
1$
#428000
b1000 +
0$
#430000
b1000 1
b11101001 -
b11101001 /
1$
#432000
b0 1
b0 -
b0 /
0!
b0 +
0#
0*
0$
#434000
1$
#436000
1!
b1 +
1#
1*
0$
#438000
b1 1
b1 -
b1 /
1$
#440000
b10 +
0#
0*
0$
#442000
b10 1
1$
#444000
b11 +
0$
#446000
b11 1
1$
#448000
b100 +
1#
1*
0$
#450000
b100 1
b1001 -
b1001 /
1$
#452000
b101 +
0#
0*
0$
#454000
b101 1
1$
#456000
b110 +
1#
1*
0$
#458000
b110 1
b101001 -
b101001 /
1$
#460000
b111 +
0$
#462000
b111 1
b1101001 -
b1101001 /
1$
#464000
b1000 +
0$
#466000
b1000 1
b11101001 -
b11101001 /
1$
#468000
b0 1
b0 -
b0 /
0!
b0 +
0#
0*
0$
#470000
1$
#472000
1!
b1 +
1#
1*
0$
#474000
b1 1
b1 -
b1 /
1$
#476000
b10 +
0#
0*
0$
#478000
b10 1
1$
#480000
b11 +
0$
#482000
b11 1
1$
#484000
b100 +
1#
1*
0$
#486000
b100 1
b1001 -
b1001 /
1$
#488000
b101 +
0#
0*
0$
#490000
b101 1
1$
#492000
b110 +
1#
1*
0$
#494000
b110 1
b101001 -
b101001 /
1$
#496000
b111 +
0$
#498000
b111 1
b1101001 -
b1101001 /
1$
#500000
b1000 +
0$
#501000
0%
#502000
b1000 1
b11101001 -
b11101001 /
1$
#504000
b0 1
b0 -
b0 /
0!
b0 +
0#
0*
0$
#506000
1$
#508000
1!
b1 +
1#
1*
0$
#510000
b1 1
b1 -
b1 /
1$
#512000
b10 +
0#
0*
0$
#514000
b10 1
1$
#516000
b11 +
0$
#518000
b11 1
1$
#520000
b100 +
1#
1*
0$
#522000
b100 1
b1001 -
b1001 /
1$
#524000
b101 +
0#
0*
0$
#526000
b101 1
1$
#528000
b110 +
1#
1*
0$
#530000
b110 1
b101001 -
b101001 /
1$
#532000
b111 +
0$
#534000
b111 1
b1101001 -
b1101001 /
1$
#536000
b1000 +
0$
#538000
b1000 1
b11101001 -
b11101001 /
1$
#540000
b0 1
b0 -
b0 /
0!
b0 +
0#
0*
0$
#542000
1$
#544000
1!
b1 +
1#
1*
0$
#546000
b1 1
b1 -
b1 /
1$
#548000
b10 +
0#
0*
0$
#550000
b10 1
1$
#552000
b11 +
0$
#554000
b11 1
1$
#556000
b100 +
1#
1*
0$
#558000
b100 1
b1001 -
b1001 /
1$
#560000
b101 +
0#
0*
0$
#562000
b101 1
1$
#564000
b110 +
1#
1*
0$
#566000
b110 1
b101001 -
b101001 /
1$
#568000
b111 +
0$
#570000
b111 1
b1101001 -
b1101001 /
1$
#572000
b1000 +
0$
#574000
b1000 1
b11101001 -
b11101001 /
1$
#576000
b0 1
b0 -
b0 /
0!
b0 +
0#
0*
0$
#578000
1$
#580000
1!
b1 +
1#
1*
0$
#582000
b1 1
b1 -
b1 /
1$
#584000
b10 +
0#
0*
0$
#586000
b10 1
1$
#588000
b11 +
0$
#590000
b11 1
1$
#592000
b100 +
1#
1*
0$
#594000
b100 1
b1001 -
b1001 /
1$
#596000
b101 +
0#
0*
0$
#598000
b101 1
1$
#600000
b110 +
1#
1*
0$
#602000
b110 1
b101001 -
b101001 /
1$
#604000
b111 +
0$
#606000
b111 1
b1101001 -
b1101001 /
1$
#608000
b1000 +
0$
#610000
b1000 1
b11101001 -
b11101001 /
1$
#612000
b0 1
b0 -
b0 /
0!
b0 +
0#
0*
0$
#614000
1$
#616000
1!
b1 +
1#
1*
0$
#618000
b1 1
b1 -
b1 /
1$
#620000
b10 +
0#
0*
0$
#622000
b10 1
1$
#624000
b11 +
0$
#626000
b11 1
1$
#628000
b100 +
1#
1*
0$
#630000
b100 1
b1001 -
b1001 /
1$
#632000
b101 +
0#
0*
0$
#634000
b101 1
1$
#636000
b110 +
1#
1*
0$
#638000
b110 1
b101001 -
b101001 /
1$
#640000
b111 +
0$
#642000
b111 1
b1101001 -
b1101001 /
1$
#644000
b1000 +
0$
#646000
b1000 1
b11101001 -
b11101001 /
1$
#648000
b0 1
b0 -
b0 /
0!
b0 +
0#
0*
0$
#650000
1$
#652000
1!
b1 +
1#
1*
0$
#654000
b1 1
b1 -
b1 /
1$
#656000
b10 +
0#
0*
0$
#658000
b10 1
1$
#660000
b11 +
0$
#662000
b11 1
1$
#664000
b100 +
1#
1*
0$
#666000
b100 1
b1001 -
b1001 /
1$
#668000
b101 +
0#
0*
0$
#670000
b101 1
1$
#672000
b110 +
1#
1*
0$
#674000
b110 1
b101001 -
b101001 /
1$
#676000
b111 +
0$
#678000
b111 1
b1101001 -
b1101001 /
1$
#680000
b1000 +
0$
#682000
b1000 1
b11101001 -
b11101001 /
1$
#684000
b0 1
b0 -
b0 /
0!
b0 +
0#
0*
0$
#686000
1$
#688000
1!
b1 +
1#
1*
0$
#690000
b1 1
b1 -
b1 /
1$
#692000
b10 +
0#
0*
0$
#694000
b10 1
1$
#696000
b11 +
0$
#698000
b11 1
1$
#700000
b100 +
1#
1*
0$
#702000
b100 1
b1001 -
b1001 /
1$
#704000
b101 +
0#
0*
0$
#706000
b101 1
1$
#708000
b110 +
1#
1*
0$
#710000
b110 1
b101001 -
b101001 /
1$
#712000
b111 +
0$
#714000
b111 1
b1101001 -
b1101001 /
1$
#716000
b1000 +
0$
#718000
b1000 1
b11101001 -
b11101001 /
1$
#720000
b0 1
b0 -
b0 /
0!
b0 +
0#
0*
0$
#722000
1$
#724000
1!
b1 +
1#
1*
0$
#726000
b1 1
b1 -
b1 /
1$
#728000
b10 +
0#
0*
0$
#730000
b10 1
1$
#732000
b11 +
0$
#734000
b11 1
1$
#736000
b100 +
1#
1*
0$
#738000
b100 1
b1001 -
b1001 /
1$
#740000
b101 +
0#
0*
0$
#742000
b101 1
1$
#744000
b110 +
1#
1*
0$
#746000
b110 1
b101001 -
b101001 /
1$
#748000
b111 +
0$
#750000
b111 1
b1101001 -
b1101001 /
1$
#752000
b1000 +
0$
#754000
b1000 1
b11101001 -
b11101001 /
1$
#756000
b0 1
b0 -
b0 /
0!
b0 +
0#
0*
0$
#758000
1$
#760000
1!
b1 +
1#
1*
0$
#762000
b1 1
b1 -
b1 /
1$
#764000
b10 +
0#
0*
0$
#766000
b10 1
1$
#768000
b11 +
0$
#770000
b11 1
1$
#772000
b100 +
1#
1*
0$
#774000
b100 1
b1001 -
b1001 /
1$
#776000
b101 +
0#
0*
0$
#778000
b101 1
1$
#780000
b110 +
1#
1*
0$
#782000
b110 1
b101001 -
b101001 /
1$
#784000
b111 +
0$
#786000
b111 1
b1101001 -
b1101001 /
1$
#788000
b1000 +
0$
#790000
b1000 1
b11101001 -
b11101001 /
1$
#792000
b0 1
b0 -
b0 /
0!
b0 +
0#
0*
0$
#794000
1$
#796000
1!
b1 +
1#
1*
0$
#798000
b1 1
b1 -
b1 /
1$
#800000
b10 +
0#
0*
0$
#802000
b10 1
1$
#804000
b11 +
0$
#806000
b11 1
1$
#808000
b100 +
1#
1*
0$
#810000
b100 1
b1001 -
b1001 /
1$
#812000
b101 +
0#
0*
0$
#814000
b101 1
1$
#816000
b110 +
1#
1*
0$
#818000
b110 1
b101001 -
b101001 /
1$
#820000
b111 +
0$
#822000
b111 1
b1101001 -
b1101001 /
1$
#824000
b1000 +
0$
#826000
b1000 1
b11101001 -
b11101001 /
1$
#828000
b0 1
b0 -
b0 /
0!
b0 +
0#
0*
0$
#830000
1$
#832000
1!
b1 +
1#
1*
0$
#834000
b1 1
b1 -
b1 /
1$
#836000
b10 +
0#
0*
0$
#838000
b10 1
1$
#840000
b11 +
0$
#842000
b11 1
1$
#844000
b100 +
1#
1*
0$
#846000
b100 1
b1001 -
b1001 /
1$
#848000
b101 +
0#
0*
0$
#850000
b101 1
1$
#852000
b110 +
1#
1*
0$
#854000
b110 1
b101001 -
b101001 /
1$
#856000
b111 +
0$
#858000
b111 1
b1101001 -
b1101001 /
1$
#860000
b1000 +
0$
#862000
b1000 1
b11101001 -
b11101001 /
1$
#864000
b0 1
b0 -
b0 /
0!
b0 +
0#
0*
0$
#866000
1$
#868000
1!
b1 +
1#
1*
0$
#870000
b1 1
b1 -
b1 /
1$
#872000
b10 +
0#
0*
0$
#874000
b10 1
1$
#876000
b11 +
0$
#878000
b11 1
1$
#880000
b100 +
1#
1*
0$
#882000
b100 1
b1001 -
b1001 /
1$
#884000
b101 +
0#
0*
0$
#886000
b101 1
1$
#888000
b110 +
1#
1*
0$
#890000
b110 1
b101001 -
b101001 /
1$
#892000
b111 +
0$
#894000
b111 1
b1101001 -
b1101001 /
1$
#896000
b1000 +
0$
#898000
b1000 1
b11101001 -
b11101001 /
1$
#900000
b0 1
b0 -
b0 /
0!
b0 +
0#
0*
0$
#902000
1$
#904000
1!
b1 +
1#
1*
0$
#906000
b1 1
b1 -
b1 /
1$
#908000
b10 +
0#
0*
0$
#910000
b10 1
1$
#912000
b11 +
0$
#914000
b11 1
1$
#916000
b100 +
1#
1*
0$
#918000
b100 1
b1001 -
b1001 /
1$
#920000
b101 +
0#
0*
0$
#922000
b101 1
1$
#924000
b110 +
1#
1*
0$
#926000
b110 1
b101001 -
b101001 /
1$
#928000
b111 +
0$
#930000
b111 1
b1101001 -
b1101001 /
1$
#932000
b1000 +
0$
#934000
b1000 1
b11101001 -
b11101001 /
1$
#936000
b0 1
b0 -
b0 /
0!
b0 +
0#
0*
0$
#938000
1$
#940000
1!
b1 +
1#
1*
0$
#942000
b1 1
b1 -
b1 /
1$
#944000
b10 +
0#
0*
0$
#946000
b10 1
1$
#948000
b11 +
0$
#950000
b11 1
1$
#952000
b100 +
1#
1*
0$
#954000
b100 1
b1001 -
b1001 /
1$
#956000
b101 +
0#
0*
0$
#958000
b101 1
1$
#960000
b110 +
1#
1*
0$
#962000
b110 1
b101001 -
b101001 /
1$
#964000
b111 +
0$
#966000
b111 1
b1101001 -
b1101001 /
1$
#968000
b1000 +
0$
#970000
b1000 1
b11101001 -
b11101001 /
1$
#972000
b0 1
b0 -
b0 /
0!
b0 +
0#
0*
0$
#974000
1$
#976000
1!
b1 +
1#
1*
0$
#978000
b1 1
b1 -
b1 /
1$
#980000
b10 +
0#
0*
0$
#982000
b10 1
1$
#984000
b11 +
0$
#986000
b11 1
1$
#988000
b100 +
1#
1*
0$
#990000
b100 1
b1001 -
b1001 /
1$
#992000
b101 +
0#
0*
0$
#994000
b101 1
1$
#996000
b110 +
1#
1*
0$
#998000
b110 1
b101001 -
b101001 /
1$
#1000000
b111 +
0$
